{
  "name": "PS Vita",
  "forums_uri": "http://forums.emunova.net/forum/25-sony/",
  "type": "Console portable",
  "released": 2011,
  "manufacturer": "Sony",
  "alternate_names": [
    "PlayStation Vita"
  ],
  "cpu": "ARM Cortex-A9 MPCore @ 2GHz",
  "ram": "512 MB RAM, 128 MB VRAM",
  "rom": "Quantité de ROM indisponible mais cette dernière stocke l'OS LiveArea de la PS Vita.",
  "video": "960x544, Quad-core PowerVR SGX543MP4+ @ 400 Mhz.",
  "media": ["Carte PlayStation Vita de 2 à 4Go de stockage."]
}
